{"annotatable":{"parts":["s1p1"]},"anncomplete":true,"sources":[],"metas":{},"entities":[{"classId":"e_1","part":"s1p1","offsets":[{"start":31,"text":"lobster"}],"coordinates":[],"confidence":{"state":"pre-added","who":["user:abhirup7"],"prob":1},"fields":{},"normalizations":{}},{"classId":"e_1","part":"s1p1","offsets":[{"start":69,"text":"lobster"}],"coordinates":[],"confidence":{"state":"pre-added","who":["ml:regex"],"prob":0},"fields":{},"normalizations":{}},{"classId":"e_1","part":"s1p1","offsets":[{"start":223,"text":"rolls"}],"coordinates":[],"confidence":{"state":"pre-added","who":["user:abhirup7"],"prob":1},"fields":{},"normalizations":{}},{"classId":"e_1","part":"s1p1","offsets":[{"start":230,"text":"grilled cheese"}],"coordinates":[],"confidence":{"state":"pre-added","who":["user:abhirup7"],"prob":1},"fields":{},"normalizations":{}},{"classId":"e_1","part":"s1p1","offsets":[{"start":321,"text":"lobster"}],"coordinates":[],"confidence":{"state":"pre-added","who":["ml:regex"],"prob":0},"fields":{},"normalizations":{}},{"classId":"e_1","part":"s1p1","offsets":[{"start":321,"text":"lobster roll combo"}],"coordinates":[],"confidence":{"state":"pre-added","who":["user:abhirup7"],"prob":1},"fields":{},"normalizations":{}},{"classId":"e_1","part":"s1p1","offsets":[{"start":350,"text":"chips"}],"coordinates":[],"confidence":{"state":"pre-added","who":["user:abhirup7"],"prob":1},"fields":{},"normalizations":{}},{"classId":"e_1","part":"s1p1","offsets":[{"start":359,"text":"slaw"}],"coordinates":[],"confidence":{"state":"pre-added","who":["user:abhirup7"],"prob":1},"fields":{},"normalizations":{}},{"classId":"e_1","part":"s1p1","offsets":[{"start":382,"text":"roll"}],"coordinates":[],"confidence":{"state":"pre-added","who":["user:abhirup7"],"prob":1},"fields":{},"normalizations":{}},{"classId":"e_1","part":"s1p1","offsets":[{"start":439,"text":"lobster"}],"coordinates":[],"confidence":{"state":"pre-added","who":["ml:regex"],"prob":0},"fields":{},"normalizations":{}},{"classId":"e_1","part":"s1p1","offsets":[{"start":524,"text":"lobster"}],"coordinates":[],"confidence":{"state":"pre-added","who":["ml:regex"],"prob":0},"fields":{},"normalizations":{}},{"classId":"e_1","part":"s1p1","offsets":[{"start":839,"text":"roll"}],"coordinates":[],"confidence":{"state":"pre-added","who":["ml:regex"],"prob":0},"fields":{},"normalizations":{}},{"classId":"e_1","part":"s1p1","offsets":[{"start":878,"text":"lobster"}],"coordinates":[],"confidence":{"state":"pre-added","who":["ml:regex"],"prob":0},"fields":{},"normalizations":{}},{"classId":"e_1","part":"s1p1","offsets":[{"start":1026,"text":"roll"}],"coordinates":[],"confidence":{"state":"pre-added","who":["ml:regex"],"prob":0},"fields":{},"normalizations":{}},{"classId":"e_1","part":"s1p1","offsets":[{"start":1122,"text":"slaw"}],"coordinates":[],"confidence":{"state":"pre-added","who":["ml:regex"],"prob":0},"fields":{},"normalizations":{}},{"classId":"e_1","part":"s1p1","offsets":[{"start":1195,"text":"soda"}],"coordinates":[],"confidence":{"state":"pre-added","who":["user:abhirup7"],"prob":1},"fields":{},"normalizations":{}},{"classId":"e_1","part":"s1p1","offsets":[{"start":1211,"text":"blueberry honey lemonade"}],"coordinates":[],"confidence":{"state":"pre-added","who":["user:abhirup7"],"prob":1},"fields":{},"normalizations":{}},{"classId":"e_1","part":"s1p1","offsets":[{"start":1478,"text":"lobster"}],"coordinates":[],"confidence":{"state":"pre-added","who":["ml:regex"],"prob":0},"fields":{},"normalizations":{}}],"relations":[]}